astraeus/__init__.py
astraeus/dataset.py
astraeus/hdf5IO.py
astraeus/xarrayIO.py
astraeus_io-1.0.dist-info/licenses/LICENSE
astraeus_io-1.0.dist-info/METADATA
astraeus_io-1.0.dist-info/WHEEL
astraeus_io-1.0.dist-info/top_level.txt
astraeus_io-1.0.dist-info/RECORD
