Metadata-Version: 2.4
Name: astraeus-io
Version: 1.0
Summary: Exoplanet data reduction I/O with xarray and netCDF support
Home-page: https://github.com/kevin218/Astraeus
Author: Kevin B. Stevenson
Author-email: kbstevenson@gmail.com
License: BSD-3-Clause
Project-URL: Bug Tracker, https://github.com/kevin218/Astraeus/issues
Project-URL: Source Code, https://github.com/kevin218/Astraeus
Classifier: Development Status :: 5 - Production/Stable
Classifier: Intended Audience :: Science/Research
Classifier: Topic :: Scientific/Engineering :: Astronomy
Classifier: Programming Language :: Python :: 3
Classifier: License :: OSI Approved :: BSD License
Classifier: Operating System :: OS Independent
Requires-Python: >=3.8
License-File: LICENSE
Requires-Dist: h5py
Requires-Dist: xarray
Requires-Dist: dask
Requires-Dist: netCDF4
Requires-Dist: h5netcdf
Requires-Dist: bottleneck
Provides-Extra: docs
Requires-Dist: sphinx; extra == "docs"
Requires-Dist: sphinx-automodapi; extra == "docs"
Requires-Dist: numpydoc; extra == "docs"
Provides-Extra: test
Requires-Dist: pytest; extra == "test"
Requires-Dist: pytest-doctestplus; extra == "test"
Requires-Dist: flake8; extra == "test"
Requires-Dist: codecov; extra == "test"
Requires-Dist: pytest-cov; extra == "test"
Provides-Extra: dev
Requires-Dist: build; extra == "dev"
Requires-Dist: twine; extra == "dev"
Dynamic: license-file
